{"trial_id": "014", "hyperparameters": {"space": [{"class_name": "Fixed", "config": {"name": "validation_split", "conditions": [], "value": 0.15}}, {"class_name": "Fixed", "config": {"name": "lag", "conditions": [], "value": 30}}, {"class_name": "Float", "config": {"name": "learning_rate", "default": 0.001, "conditions": [], "min_value": 0.001, "max_value": 0.01, "step": null, "sampling": "linear"}}, {"class_name": "Float", "config": {"name": "w0", "default": 0.0, "conditions": [], "min_value": 0.0, "max_value": 1.0, "step": null, "sampling": "linear"}}, {"class_name": "Float", "config": {"name": "w1", "default": 0.0, "conditions": [], "min_value": 0.0, "max_value": 1.0, "step": null, "sampling": "linear"}}, {"class_name": "Float", "config": {"name": "w2", "default": 0.0, "conditions": [], "min_value": 0.0, "max_value": 1.0, "step": null, "sampling": "linear"}}, {"class_name": "Float", "config": {"name": "w3", "default": 0.0, "conditions": [], "min_value": 0.0, "max_value": 1.0, "step": null, "sampling": "linear"}}, {"class_name": "Float", "config": {"name": "w4", "default": 0.0, "conditions": [], "min_value": 0.0, "max_value": 1.0, "step": null, "sampling": "linear"}}, {"class_name": "Float", "config": {"name": "w5", "default": 0.0, "conditions": [], "min_value": 0.0, "max_value": 1.0, "step": null, "sampling": "linear"}}, {"class_name": "Float", "config": {"name": "w6", "default": 0.0, "conditions": [], "min_value": 0.0, "max_value": 1.0, "step": null, "sampling": "linear"}}, {"class_name": "Float", "config": {"name": "w7", "default": 0.0, "conditions": [], "min_value": 0.0, "max_value": 1.0, "step": null, "sampling": "linear"}}, {"class_name": "Float", "config": {"name": "w8", "default": 0.0, "conditions": [], "min_value": 0.0, "max_value": 1.0, "step": null, "sampling": "linear"}}, {"class_name": "Float", "config": {"name": "w9", "default": 0.0, "conditions": [], "min_value": 0.0, "max_value": 1.0, "step": null, "sampling": "linear"}}, {"class_name": "Float", "config": {"name": "w10", "default": 0.0, "conditions": [], "min_value": 0.0, "max_value": 1.0, "step": null, "sampling": "linear"}}, {"class_name": "Float", "config": {"name": "w11", "default": 0.0, "conditions": [], "min_value": 0.0, "max_value": 1.0, "step": null, "sampling": "linear"}}, {"class_name": "Float", "config": {"name": "w12", "default": 0.0, "conditions": [], "min_value": 0.0, "max_value": 1.0, "step": null, "sampling": "linear"}}, {"class_name": "Float", "config": {"name": "w13", "default": 0.0, "conditions": [], "min_value": 0.0, "max_value": 1.0, "step": null, "sampling": "linear"}}, {"class_name": "Float", "config": {"name": "w14", "default": 0.0, "conditions": [], "min_value": 0.0, "max_value": 1.0, "step": null, "sampling": "linear"}}, {"class_name": "Float", "config": {"name": "w15", "default": 0.0, "conditions": [], "min_value": 0.0, "max_value": 1.0, "step": null, "sampling": "linear"}}, {"class_name": "Float", "config": {"name": "w16", "default": 0.0, "conditions": [], "min_value": 0.0, "max_value": 1.0, "step": null, "sampling": "linear"}}, {"class_name": "Float", "config": {"name": "w17", "default": 0.0, "conditions": [], "min_value": 0.0, "max_value": 1.0, "step": null, "sampling": "linear"}}, {"class_name": "Float", "config": {"name": "w18", "default": 0.0, "conditions": [], "min_value": 0.0, "max_value": 1.0, "step": null, "sampling": "linear"}}, {"class_name": "Float", "config": {"name": "w19", "default": 0.0, "conditions": [], "min_value": 0.0, "max_value": 1.0, "step": null, "sampling": "linear"}}, {"class_name": "Float", "config": {"name": "w20", "default": 0.0, "conditions": [], "min_value": 0.0, "max_value": 1.0, "step": null, "sampling": "linear"}}, {"class_name": "Float", "config": {"name": "w21", "default": 0.0, "conditions": [], "min_value": 0.0, "max_value": 1.0, "step": null, "sampling": "linear"}}, {"class_name": "Float", "config": {"name": "w22", "default": 0.0, "conditions": [], "min_value": 0.0, "max_value": 1.0, "step": null, "sampling": "linear"}}, {"class_name": "Float", "config": {"name": "w23", "default": 0.0, "conditions": [], "min_value": 0.0, "max_value": 1.0, "step": null, "sampling": "linear"}}, {"class_name": "Float", "config": {"name": "w24", "default": 0.0, "conditions": [], "min_value": 0.0, "max_value": 1.0, "step": null, "sampling": "linear"}}, {"class_name": "Float", "config": {"name": "w25", "default": 0.0, "conditions": [], "min_value": 0.0, "max_value": 1.0, "step": null, "sampling": "linear"}}, {"class_name": "Float", "config": {"name": "w26", "default": 0.0, "conditions": [], "min_value": 0.0, "max_value": 1.0, "step": null, "sampling": "linear"}}, {"class_name": "Float", "config": {"name": "w27", "default": 0.0, "conditions": [], "min_value": 0.0, "max_value": 1.0, "step": null, "sampling": "linear"}}, {"class_name": "Float", "config": {"name": "w28", "default": 0.0, "conditions": [], "min_value": 0.0, "max_value": 1.0, "step": null, "sampling": "linear"}}, {"class_name": "Float", "config": {"name": "w29", "default": 0.0, "conditions": [], "min_value": 0.0, "max_value": 1.0, "step": null, "sampling": "linear"}}, {"class_name": "Int", "config": {"name": "K", "default": 3, "conditions": [], "min_value": 3, "max_value": 6, "step": 1, "sampling": "linear"}}, {"class_name": "Int", "config": {"name": "alpha", "default": 1000, "conditions": [], "min_value": 1000, "max_value": 5000, "step": 1, "sampling": "linear"}}, {"class_name": "Int", "config": {"name": "epochs", "default": 20, "conditions": [], "min_value": 20, "max_value": 50, "step": 1, "sampling": "linear"}}, {"class_name": "Int", "config": {"name": "batch_size", "default": 8, "conditions": [], "min_value": 8, "max_value": 64, "step": 4, "sampling": "linear"}}, {"class_name": "Int", "config": {"name": "units", "default": 16, "conditions": [], "min_value": 16, "max_value": 96, "step": 1, "sampling": "linear"}}], "values": {"validation_split": 0.15, "lag": 30, "learning_rate": 0.01, "w0": 0.5411881785127259, "w1": 0.06704633270727144, "w2": 0.12304974724297733, "w3": 0.4833494083755193, "w4": 0.6383539959582588, "w5": 0.3617675468125561, "w6": 0.9699751619407783, "w7": 0.7567100635576736, "w8": 0.12261041564923551, "w9": 0.1907796670300851, "w10": 0.3283740167561246, "w11": 0.5332453182775418, "w12": 0.6064001188618265, "w13": 0.5823946202570357, "w14": 0.7445510499104835, "w15": 0.2850725302172713, "w16": 0.7931930798921079, "w17": 0.27153955059584595, "w18": 0.6626202615757539, "w19": 0.22538931664419296, "w20": 0.19794160608003167, "w21": 0.11317640057291499, "w22": 0.9242706666012865, "w23": 0.2769236441667094, "w24": 0.5475451642341305, "w25": 0.9007979229057175, "w26": 0.7477145464384881, "w27": 0.054848726198309876, "w28": 0.4254852275476565, "w29": 0.9584209381111028, "K": 4, "alpha": 4093, "epochs": 48, "batch_size": 15, "units": 53}}, "metrics": {"metrics": {"rmse": {"direction": "min", "observations": [{"value": [7791.308196309643], "step": 0}]}, "mae": {"direction": "min", "observations": [{"value": [7161.893272210744], "step": 0}]}, "r2": {"direction": "min", "observations": [{"value": [-5.374298993941439], "step": 0}]}, "mape": {"direction": "min", "observations": [{"value": [0.19040212807887782], "step": 0}]}, "mse": {"direction": "min", "observations": [{"value": [60704483.40988182], "step": 0}]}, "da": {"direction": "min", "observations": [{"value": [0.4723756906077348], "step": 0}]}}}, "score": 60704483.40988182, "best_step": 0, "status": "COMPLETED", "message": null}